aruw_pathfinding-0.5.0.dist-info/METADATA
aruw_pathfinding-0.5.0.dist-info/WHEEL
aruw_pathfinding-0.5.0.dist-info/license_files/LICENSE
aruw_pathfinding/__init__.py
aruw_pathfinding/__init__.pyi
aruw_pathfinding/py.typed
aruw_pathfinding/aruw_pathfinding.cpython-310-darwin.so
aruw_pathfinding-0.5.0.dist-info/RECORD
