Metadata-Version: 2.1
Name: aruw-pathfinding
Version: 0.5.0
Classifier: Programming Language :: Rust
Classifier: Programming Language :: Python :: Implementation :: CPython
Classifier: Programming Language :: Python :: Implementation :: PyPy
License-File: LICENSE
Summary: A* and D* algorithms for pathfinding from an input list squares
Author-email: Max McKelvey <mckelvey.max.o@gmail.com>
Requires-Python: >=3.10
